TracSimpleTicket-5.0.dist-info/DESCRIPTION.rst
TracSimpleTicket-5.0.dist-info/METADATA
TracSimpleTicket-5.0.dist-info/RECORD
TracSimpleTicket-5.0.dist-info/WHEEL
TracSimpleTicket-5.0.dist-info/entry_points.txt
TracSimpleTicket-5.0.dist-info/metadata.json
TracSimpleTicket-5.0.dist-info/top_level.txt
simpleticket/__init__.py
simpleticket/web_ui.py
