Metadata-Version: 2.0
Name: TracSimpleTicket
Version: 5.0
Summary: Restricted ticket entry form for Trac
Home-page: https://trac-hacks.org/wiki/SimpleTicketPlugin
Author: Ryan J Ollos
Author-email: ryan.j.ollos@gmail.com
License: 3-Clause BSD
Keywords: trac plugin restricted ticket
Platform: UNKNOWN
Classifier: Framework :: Trac
Requires-Dist: Trac
